doc2talk/__init__.py
doc2talk/__main__.py
doc2talk/cli.py
doc2talk/core.py
doc2talk/doc2talk.py
doc2talk/docgraph.py
doc2talk/models.py
doc2talk-0.1.1.dist-info/METADATA
doc2talk-0.1.1.dist-info/WHEEL
doc2talk-0.1.1.dist-info/entry_points.txt
doc2talk-0.1.1.dist-info/licenses/LICENSE
doc2talk-0.1.1.dist-info/RECORD
