Metadata-Version: 2.4
Name: doc2talk
Version: 0.1.1
Summary: A library that enables a hallucination-free conversations with code repositories.
Project-URL: Homepage, https://github.com/unclecode/doc2talk
Project-URL: Issues, https://github.com/unclecode/doc2talk/issues
Project-URL: Documentation, https://doc2talk.readthedocs.io/
Author-email: Your Name <your.email@example.com>
License: MIT
License-File: LICENSE
Classifier: Development Status :: 3 - Alpha
Classifier: Intended Audience :: Developers
Classifier: License :: OSI Approved :: MIT License
Classifier: Programming Language :: Python :: 3
Classifier: Programming Language :: Python :: 3.8
Classifier: Programming Language :: Python :: 3.9
Classifier: Programming Language :: Python :: 3.10
Classifier: Programming Language :: Python :: 3.11
Requires-Python: >=3.8
Requires-Dist: litellm>=1.63.7
Requires-Dist: msgpack>=1.0.5
Requires-Dist: pydantic>=2.0.0
Requires-Dist: requests>=2.28.0
Requires-Dist: rich>=13.9.4
Requires-Dist: zstandard>=0.20.0
Provides-Extra: dev
Requires-Dist: black>=23.0.0; extra == 'dev'
Requires-Dist: isort>=5.12.0; extra == 'dev'
Requires-Dist: mypy>=1.0.0; extra == 'dev'
Requires-Dist: pytest-cov>=4.0.0; extra == 'dev'
Requires-Dist: pytest>=7.0.0; extra == 'dev'
Requires-Dist: ruff>=0.1.0; extra == 'dev'
